numdata1/__init__.py
numdata1/calculate.py
numdata1-0.0.1.dist-info/LICENSE
numdata1-0.0.1.dist-info/METADATA
numdata1-0.0.1.dist-info/WHEEL
numdata1-0.0.1.dist-info/top_level.txt
numdata1-0.0.1.dist-info/RECORD
