Metadata-Version: 2.1
Name: numdata1
Version: 0.0.1
Summary: A simple package calculating valuews for a simple number
Home-page: UNKNOWN
Author: Charles Chen
Author-email: yc414@duke.edu
License: UNKNOWN
Keywords: package numbers calculations
Platform: UNKNOWN
Classifier: Programming Language :: Python :: 2
Classifier: Operating System :: OS Independent
